product_association/__init__.py
product_association/association_analysis.py
product_association/cli.py
product_association/data_loader.py
product_association/report_generator.py
product_association_analysis-0.1.2.dist-info/METADATA
product_association_analysis-0.1.2.dist-info/WHEEL
product_association_analysis-0.1.2.dist-info/entry_points.txt
product_association_analysis-0.1.2.dist-info/top_level.txt
product_association_analysis-0.1.2.dist-info/RECORD
